setup.py
default_dont_cache/__init__.py
default_dont_cache/decorators.py
default_dont_cache/middleware.py
django_default_dont_cache.egg-info/PKG-INFO
django_default_dont_cache.egg-info/SOURCES.txt
django_default_dont_cache.egg-info/dependency_links.txt
django_default_dont_cache.egg-info/requires.txt
django_default_dont_cache.egg-info/top_level.txt