Metadata-Version: 1.0
Name: django-default-dont-cache
Version: 0.1.0
Summary: Opt-in caching for Django's per-site cache
Home-page: UNKNOWN
Author: Rory McCann
Author-email: rory@technomancy.org
License: GPLv3
Platform: UNKNOWN
